openjd/sessions/__init__.py
openjd/sessions/_action_filter.py
openjd/sessions/_embedded_files.py
openjd/sessions/_logging.py
openjd/sessions/_os_checker.py
openjd/sessions/_path_mapping.py
openjd/sessions/_runner_base.py
openjd/sessions/_runner_env_script.py
openjd/sessions/_runner_step_script.py
openjd/sessions/_session.py
openjd/sessions/_session_user.py
openjd/sessions/_subprocess.py
openjd/sessions/_tempdir.py
openjd/sessions/_types.py
openjd/sessions/_version.py
openjd/sessions/_windows_permission_helper.py
openjd/sessions/_windows_process_killer.py
openjd/sessions/py.typed
openjd/sessions/_linux/__init__.py
openjd/sessions/_linux/_capabilities.py
openjd/sessions/_linux/_sudo.py
openjd/sessions/_scripts/_posix/_signal_subprocess.sh
openjd/sessions/_scripts/_windows/_signal_win_subprocess.py
openjd/sessions/_win32/__init__.py
openjd/sessions/_win32/_api.py
openjd/sessions/_win32/_helpers.py
openjd/sessions/_win32/_locate_executable.py
openjd/sessions/_win32/_popen_as_user.py
openjd_sessions-0.10.6.dist-info/METADATA
openjd_sessions-0.10.6.dist-info/WHEEL
openjd_sessions-0.10.6.dist-info/licenses/LICENSE
openjd_sessions-0.10.6.dist-info/licenses/NOTICE
openjd_sessions-0.10.6.dist-info/RECORD
