Metadata-Version: 2.4
Name: openjd-sessions
Version: 0.10.6
Summary: Provides a library that can be used to build a runtime that is able to run Jobs in a Session as defined by Open Job Description.
Project-URL: Homepage, https://github.com/OpenJobDescription/openjd-sessions-for-python
Project-URL: Source, https://github.com/OpenJobDescription/openjd-sessions-for-python
Author: Amazon Web Services
License-Expression: Apache-2.0
License-File: LICENSE
License-File: NOTICE
Classifier: Development Status :: 5 - Production/Stable
Classifier: Intended Audience :: Developers
Classifier: License :: OSI Approved :: Apache Software License
Classifier: Operating System :: MacOS
Classifier: Operating System :: Microsoft :: Windows
Classifier: Operating System :: POSIX :: Linux
Classifier: Programming Language :: Python
Classifier: Programming Language :: Python :: 3 :: Only
Classifier: Programming Language :: Python :: 3.9
Classifier: Programming Language :: Python :: 3.10
Classifier: Programming Language :: Python :: 3.11
Classifier: Programming Language :: Python :: 3.12
Classifier: Topic :: Software Development :: Libraries
Requires-Python: >=3.9
Requires-Dist: openjd-model<0.9,>=0.8
Requires-Dist: psutil<7.2,>=5.9; platform_system == 'Windows'
Requires-Dist: pywin32>=307; platform_system == 'Windows'
